pyqt5_auto_translate/TranslatedItems.py
pyqt5_auto_translate/__init__.py
pyqt5_auto_translate/example.ui
pyqt5_auto_translate/translations.yml
pyqt5_auto_translate-0.1.1.dist-info/LICENSE
pyqt5_auto_translate-0.1.1.dist-info/METADATA
pyqt5_auto_translate-0.1.1.dist-info/WHEEL
pyqt5_auto_translate-0.1.1.dist-info/top_level.txt
pyqt5_auto_translate-0.1.1.dist-info/RECORD
