Metadata-Version: 2.1
Name: pyqt5-auto-translate
Version: 0.1.1
Summary: A lightweight and easy-to-use library for automating the translation of PyQt5 widgets.
Home-page: https://github.com/LiRunJi/pyqt5_auto_translate
Author: RunJi
Author-email: ryanlee02@foxmail.com
License: UNKNOWN
Platform: UNKNOWN
Classifier: Development Status :: 3 - Alpha
Classifier: Intended Audience :: Developers
Classifier: License :: OSI Approved :: MIT License
Classifier: Operating System :: OS Independent
Classifier: Programming Language :: Python :: 3
Classifier: Programming Language :: Python :: 3.6
Classifier: Programming Language :: Python :: 3.7
Classifier: Programming Language :: Python :: 3.8
Classifier: Programming Language :: Python :: 3.9
Classifier: Programming Language :: Python :: 3.10
Classifier: Programming Language :: Python :: 3.11
Requires-Python: >=3.6
License-File: LICENSE
Requires-Dist: PyYAML (>=5.4.1)
Requires-Dist: PyQt5 (>=5.15.4)
